dqflow/__init__.py
dqflow/cli.py
dqflow/column.py
dqflow/contract.py
dqflow/result.py
dqflow/engines/__init__.py
dqflow/engines/base.py
dqflow/engines/pandas.py
dqflow-0.1.3.dist-info/METADATA
dqflow-0.1.3.dist-info/WHEEL
dqflow-0.1.3.dist-info/entry_points.txt
dqflow-0.1.3.dist-info/licenses/LICENSE
dqflow-0.1.3.dist-info/RECORD
