Metadata-Version: 2.4
Name: dqflow
Version: 0.1.3
Summary: Lightweight, contract-first data quality engine for modern data pipelines
Project-URL: Homepage, https://github.com/dqflow/dqflow
Project-URL: Repository, https://github.com/dqflow/dqflow
Project-URL: Issues, https://github.com/dqflow/dqflow/issues
Author-email: Quang <nguyenvanquang247@gmail.com>
License-Expression: MIT
License-File: LICENSE
Keywords: data-contracts,data-quality,data-validation,etl,pandas
Classifier: Development Status :: 3 - Alpha
Classifier: Intended Audience :: Developers
Classifier: License :: OSI Approved :: MIT License
Classifier: Programming Language :: Python :: 3
Classifier: Programming Language :: Python :: 3.9
Classifier: Programming Language :: Python :: 3.10
Classifier: Programming Language :: Python :: 3.11
Classifier: Programming Language :: Python :: 3.12
Classifier: Topic :: Software Development :: Libraries :: Python Modules
Requires-Python: >=3.9
Requires-Dist: click>=8.0
Requires-Dist: pandas>=1.5.0
Requires-Dist: pyyaml>=6.0
Provides-Extra: dev
Requires-Dist: mypy>=1.0; extra == 'dev'
Requires-Dist: pandas-stubs>=2.0; extra == 'dev'
Requires-Dist: pre-commit>=3.0; extra == 'dev'
Requires-Dist: pytest-cov>=4.0; extra == 'dev'
Requires-Dist: pytest>=7.0; extra == 'dev'
Requires-Dist: ruff>=0.1.0; extra == 'dev'
Requires-Dist: types-pyyaml>=6.0; extra == 'dev'
